git_observer/__init__.py
git_observer/git_handler.py
git_observer/main.py
git_observer/utils.py
git_observer/watcher.py
gitobserver-2.0.0.dist-info/licenses/LICENCE.md
gitobserver-2.0.0.dist-info/METADATA
gitobserver-2.0.0.dist-info/WHEEL
gitobserver-2.0.0.dist-info/entry_points.txt
gitobserver-2.0.0.dist-info/top_level.txt
gitobserver-2.0.0.dist-info/RECORD
