Metadata-Version: 2.4
Name: gitobserver
Version: 2.0.0
Summary: Automotic Git tool for file commiting
Home-page: https://github.com/k2pme/gitobserver
Author: K2pme
Author-email: cmantsila0@gmail.com
Classifier: Programming Language :: Python :: 3
Classifier: License :: OSI Approved :: MIT License
Classifier: Operating System :: OS Independent
Requires-Python: >=3.6
License-File: LICENCE.md
Requires-Dist: watchdog
Requires-Dist: colorama
Dynamic: author
Dynamic: author-email
Dynamic: classifier
Dynamic: description
Dynamic: description-content-type
Dynamic: home-page
Dynamic: license-file
Dynamic: requires-dist
Dynamic: requires-python
Dynamic: summary
